mojimoji.cpython-37m-darwin.so
mojimoji2-0.1.3.dist-info/LICENSE
mojimoji2-0.1.3.dist-info/METADATA
mojimoji2-0.1.3.dist-info/WHEEL
mojimoji2-0.1.3.dist-info/top_level.txt
mojimoji2-0.1.3.dist-info/RECORD
