Metadata-Version: 2.1
Name: mojimoji2
Version: 0.1.3
Summary: A fast converter between Japanese hankaku and zenkaku characters
Home-page: http://github.com/tamuhey/mojimoji
Author: tamuhey
Author-email: tamuhey@gmail.com
License: UNKNOWN
Keywords: japanese
Platform: UNKNOWN
Classifier: Development Status :: 4 - Beta
Classifier: Intended Audience :: Developers
Classifier: Natural Language :: Japanese
Classifier: License :: OSI Approved :: Apache Software License
Classifier: Programming Language :: Python
Classifier: Programming Language :: Python :: 3
Classifier: Programming Language :: Python :: 3.5
Classifier: Programming Language :: Python :: 3.6
Classifier: Programming Language :: Python :: 3.7
